CHANGES.txt
LICENSE.txt
MANIFEST.in
README.txt
setup.py
tests/__init__.py
tests/gpx_model_tests.py
tests/waypoint_tests.py
trailer/__init__.py
trailer.egg-info/PKG-INFO
trailer.egg-info/SOURCES.txt
trailer.egg-info/dependency_links.txt
trailer.egg-info/not-zip-safe
trailer.egg-info/requires.txt
trailer.egg-info/top_level.txt
trailer/model/__init__.py
trailer/model/bounds.py
trailer/model/copyright.py
trailer/model/fieldtools.py
trailer/model/fix.py
trailer/model/gpx_model.py
trailer/model/link.py
trailer/model/metadata.py
trailer/model/person.py
trailer/model/route.py
trailer/model/segment.py
trailer/model/track.py
trailer/model/waypoint.py
trailer/model/year.py
trailer/readers/__init__.py
trailer/readers/common.py
trailer/readers/parser.py
trailer/readers/gpx_1_0/__init__.py
trailer/readers/gpx_1_0/parser.py
trailer/readers/gpx_1_1/__init__.py
trailer/readers/gpx_1_1/parser.py
trailer/validators/__init__.py
trailer/validators/gpx_1_0/__init__.py
trailer/validators/gpx_1_0/validator.py
trailer/validators/gpx_1_0/schemas/gpx_1_0.xsd
trailer/validators/gpx_1_1/__init__.py
trailer/validators/gpx_1_1/schemas/gpx_1_1.xsd
trailer/writers/__init__.py
trailer/writers/json/__init__.py
trailer/writers/json/renderer.py