Metadata-Version: 1.1
Name: trailer
Version: 0.66
Summary: A model, readers and writers for GPX 1.0 and GPX 1.1 data.
Home-page: https://github.com/rob-smallshire/trailer/
Author: Robert Smallshire
Author-email: robert@smallshire.org.uk
License: MIT License
Keywords: Python
Platform: UNKNOWN
Classifier: Development Status :: 4 - Beta
Classifier: Programming Language :: Python :: 3
Classifier: Programming Language :: Python :: 3.3
Classifier: Environment :: Other Environment
Classifier: Intended Audience :: Developers
Classifier: License :: OSI Approved :: MIT License
Classifier: Operating System :: OS Independent
Classifier: Topic :: Software Development :: Libraries :: Python Modules
Classifier: Topic :: Utilities
